BugBounty/BugBounty.py
BugBounty/__init__.py
BugBounty-6.0.dist-info/LICENSE
BugBounty-6.0.dist-info/METADATA
BugBounty-6.0.dist-info/WHEEL
BugBounty-6.0.dist-info/entry_points.txt
BugBounty-6.0.dist-info/top_level.txt
BugBounty-6.0.dist-info/RECORD
