Metadata-Version: 2.1
Name: BugBounty
Version: 6.0
Summary: BugBounty for Internet Freedom (Domain Fronting, Server Name Indication, Etc)
Home-page: https://github.com/Technoindian/BugBounty
Author: RK_TECHNO_INDIA
Author-email: TechnoIndia786@gmail.com
Classifier: Programming Language :: Python :: 3
Classifier: License :: OSI Approved :: MIT License
Classifier: Operating System :: OS Independent
Requires-Python: >=3.12
License-File: LICENSE
